Metadata-Version: 2.4
Name: trackeval
Version: 1.1.0
Summary: Different tracking evaluation metrics including HOTA metrics.
Author-email: Jonathon Luiten <jonoluiten@gmail.com>
Maintainer-email: Arne Hoffhues <unknown.email@unknownhost.com>, Jonathon Luiten <jonoluiten@gmail.com>
License: MIT
Project-URL: Repository, https://github.com/kovalp/TrackEval
Project-URL: Issues, https://github.com/kovalp/TrackEval/issues
Classifier: Programming Language :: Python :: 3
Classifier: Operating System :: OS Independent
Classifier: Topic :: Scientific/Engineering
Requires-Python: <4.0,>=3.8
License-File: LICENSE
Requires-Dist: matplotlib>=3.7.5; python_version == "3.8"
Requires-Dist: numpy<2.0,>=1.24.4; python_version == "3.8"
Requires-Dist: pillow>=10.4.0; python_version == "3.8"
Requires-Dist: pycocotools>=2.0.7; python_version == "3.8"
Requires-Dist: scikit-image>=0.21.0; python_version == "3.8"
Requires-Dist: scipy>=1.10.1; python_version == "3.8"
Requires-Dist: matplotlib>=3.9.4; python_version == "3.9"
Requires-Dist: numpy>=2.0.2; python_version == "3.9"
Requires-Dist: pillow>=11.3.0; python_version >= "3.9"
Requires-Dist: pycocotools>=2.0.10; python_version >= "3.9"
Requires-Dist: scikit-image>=0.24.0; python_version == "3.9"
Requires-Dist: scipy>=1.13.1; python_version == "3.9"
Requires-Dist: matplotlib>=3.10.5; python_version >= "3.10"
Requires-Dist: numpy>=2.2.6; python_version == "3.10"
Requires-Dist: scikit-image>=0.25.2; python_version >= "3.10"
Requires-Dist: scipy>=1.15.3; python_version == "3.10"
Requires-Dist: numpy>=2.3.2; python_version >= "3.11"
Requires-Dist: scipy>=1.16.1; python_version >= "3.11"
Requires-Dist: tabulate>=0.9.0
Requires-Dist: opencv-python>=4.11.0.86
Dynamic: license-file
